odoo10_addon_module_prototyper-10.0.1.0.0-py2.7-nspkg.pth
odoo10_addon_module_prototyper-10.0.1.0.0.dist-info/top_level.txt
odoo10_addon_module_prototyper-10.0.1.0.0.dist-info/WHEEL
odoo10_addon_module_prototyper-10.0.1.0.0.dist-info/RECORD
odoo10_addon_module_prototyper-10.0.1.0.0.dist-info/metadata.json
odoo10_addon_module_prototyper-10.0.1.0.0.dist-info/DESCRIPTION.rst
odoo10_addon_module_prototyper-10.0.1.0.0.dist-info/METADATA
odoo10_addon_module_prototyper-10.0.1.0.0.dist-info/namespace_packages.txt
odoo/addons/module_prototyper/__manifest__.py
odoo/addons/module_prototyper/__init__.py
odoo/addons/module_prototyper/README.rst
odoo/addons/module_prototyper/security/ir.model.access.csv
odoo/addons/module_prototyper/models/module_prototyper_api_version.py
odoo/addons/module_prototyper/models/module_prototyper.py
odoo/addons/module_prototyper/models/__init__.py
odoo/addons/module_prototyper/models/licenses.py
odoo/addons/module_prototyper/models/ir_model_fields.py
odoo/addons/module_prototyper/templates/10.0/__init__.py.template
odoo/addons/module_prototyper/templates/10.0/__manifest__.py.template
odoo/addons/module_prototyper/templates/10.0/header.template
odoo/addons/module_prototyper/templates/10.0/security/model_name.xml.template
odoo/addons/module_prototyper/templates/10.0/security/ir.model.access.csv.template
odoo/addons/module_prototyper/templates/10.0/models/model_name.py.template
odoo/addons/module_prototyper/templates/10.0/models/__init__.py.template
odoo/addons/module_prototyper/templates/10.0/views/model_views.xml.template
odoo/addons/module_prototyper/templates/10.0/views/model_menus.xml.template
odoo/addons/module_prototyper/templates/10.0/data/model_name.xml.template
odoo/addons/module_prototyper/templates/10.0/demo/model_name.xml.template
odoo/addons/module_prototyper/templates/8.0/__init__.py.template
odoo/addons/module_prototyper/templates/8.0/header.template
odoo/addons/module_prototyper/templates/8.0/__openerp__.py.template
odoo/addons/module_prototyper/templates/8.0/security/model_name.xml.template
odoo/addons/module_prototyper/templates/8.0/security/ir.model.access.csv.template
odoo/addons/module_prototyper/templates/8.0/models/model_name.py.template
odoo/addons/module_prototyper/templates/8.0/models/__init__.py.template
odoo/addons/module_prototyper/templates/8.0/views/model_views.xml.template
